jhmytest2508/__init__.py
jhmytest2508/core.py
jhmytest2508-1.0.0.dist-info/licenses/LICENSE
jhmytest2508-1.0.0.dist-info/METADATA
jhmytest2508-1.0.0.dist-info/WHEEL
jhmytest2508-1.0.0.dist-info/top_level.txt
jhmytest2508-1.0.0.dist-info/RECORD
