Metadata-Version: 2.4
Name: jhmytest2508
Version: 1.0.0
Summary: My First Library
Author-email: Jun Hee Han <jjunihan@hanmail.net>
License: HAN
Requires-Python: >=3.9
License-File: LICENSE
Dynamic: license-file
